tests/__init__.py
tests/conftest.py
tests/test_api.py
tests/test_client.py
tests/test_const.py
tests/test_package_init.py
tests/test_sessions.py
tests/test_utils.py
tests/models/__init__.py
tests/models/test_case.py
tests/models/test_case_type.py
tests/models/test_configs.py
tests/models/test_milestone.py
tests/models/test_model_base.py
tests/models/test_priorities.py
tests/models/test_project.py
tests/models/test_result.py
tests/models/test_run.py
tests/models/test_section.py
tests/models/test_status.py
tests/models/test_suite.py
tests/models/test_template.py
tests/models/test_test.py
tests/models/test_user.py
traw/VERSION
traw/__init__.py
traw/api.py
traw/client.py
traw/const.py
traw/exceptions.py
traw/sessions.py
traw/utils.py
traw/models/__init__.py
traw/models/case.py
traw/models/case_type.py
traw/models/config.py
traw/models/milestone.py
traw/models/model_base.py
traw/models/plan.py
traw/models/posters.py
traw/models/priority.py
traw/models/project.py
traw/models/result.py
traw/models/run.py
traw/models/section.py
traw/models/status.py
traw/models/suite.py
traw/models/template.py
traw/models/test.py
traw/models/user.py
traw-0.3.0.dist-info/AUTHORS
traw-0.3.0.dist-info/LICENSE
traw-0.3.0.dist-info/METADATA
traw-0.3.0.dist-info/WHEEL
traw-0.3.0.dist-info/top_level.txt
traw-0.3.0.dist-info/RECORD
