Metadata-Version: 2.1
Name: traw
Version: 0.3.0
Summary: Python library and CLI for interfacing with TestRail's REST API
Home-page: https://github.com/levi-rs/testrail-api-wrapper
Author: Levi Noecker
Author-email: levi.noecker@gmail.com
License: MIT
Keywords: testrail client api wrapper traw
Platform: UNKNOWN
Classifier: Development Status :: 4 - Beta
Classifier: Environment :: Console
Classifier: Intended Audience :: Developers
Classifier: License :: OSI Approved :: MIT License
Classifier: Operating System :: OS Independent
Classifier: Programming Language :: Python
Classifier: Programming Language :: Python :: 2
Classifier: Programming Language :: Python :: 2.7
Classifier: Programming Language :: Python :: 3
Classifier: Programming Language :: Python :: 3.4
Classifier: Programming Language :: Python :: 3.5
Classifier: Programming Language :: Python :: 3.6
Classifier: Programming Language :: Python :: 3.7
Classifier: Programming Language :: Python :: Implementation :: CPython
Requires-Dist: click
Requires-Dist: requests
Requires-Dist: retry
Requires-Dist: singledispatch
Requires-Dist: six
